spyx/__init__.py
spyx/_version.py
spyx/axn.py
spyx/data.py
spyx/experimental.py
spyx/fn.py
spyx/loaders.py
spyx/nir.py
spyx/nn.py
spyx-0.1.20.dist-info/LICENSE
spyx-0.1.20.dist-info/METADATA
spyx-0.1.20.dist-info/WHEEL
spyx-0.1.20.dist-info/top_level.txt
spyx-0.1.20.dist-info/RECORD
