Metadata-Version: 2.1
Name: spyx
Version: 0.1.20
Summary: Spyx: SNNs in JAX
Home-page: https://github.com/kmheckel/spyx
Author: Kade Heckel
Author-email: example@email.com
License: MIT
Classifier: Intended Audience :: Developers
Classifier: License :: OSI Approved :: MIT License
Classifier: Programming Language :: Python
Classifier: Programming Language :: Python :: 3
Classifier: Programming Language :: Python :: 3.9
Classifier: Programming Language :: Python :: 3.10
Classifier: Programming Language :: Python :: 3.11
Classifier: Programming Language :: Python :: 3.12
Classifier: Operating System :: OS Independent
License-File: LICENSE
Requires-Dist: dm-haiku
Requires-Dist: optax
Requires-Dist: jax-tqdm
Requires-Dist: nir
Provides-Extra: loaders
Requires-Dist: tonic ; extra == 'loaders'
Requires-Dist: torchvision ==0.19.0+cpu ; extra == 'loaders'
Requires-Dist: scikit-learn ; extra == 'loaders'
